argopandas/__init__.py
argopandas/_geo.py
argopandas/_interactive.py
argopandas/downloader.py
argopandas/float.py
argopandas/global_index.py
argopandas/index.py
argopandas/mirror.py
argopandas/netcdf.py
argopandas/path.py
argopandas/progress.py
argopandas-0.0.5.dist-info/LICENSE
argopandas-0.0.5.dist-info/METADATA
argopandas-0.0.5.dist-info/WHEEL
argopandas-0.0.5.dist-info/top_level.txt
argopandas-0.0.5.dist-info/RECORD
