Metadata-Version: 2.1
Name: argopandas
Version: 0.0.5
Summary: Locate, Download, and Read Argo Ocean Float Data
Home-page: https://github.com/paleolimbot/argopandas
Author: Dewey Dunnington
Author-email: dewey.dunnington@dfo-mpo.gc.ca
License: UNKNOWN
Project-URL: Bug Tracker, https://github.com/paleolimbot/argopandas/issues
Platform: UNKNOWN
Classifier: Programming Language :: Python :: 3
Classifier: License :: OSI Approved :: MIT License
Classifier: Operating System :: OS Independent
Requires-Python: >=3.6
License-File: LICENSE
Requires-Dist: netCDF4
Requires-Dist: numpy
Requires-Dist: pandas
Requires-Dist: pyarrow
